{
  "ID":["0","1","2","3","4","5","6","7","8","9","10","11"],
  "ROUND1":["-1","0","3","0","-1","0","0","3","3","-1","-1","3"],
  "ROUND2":["2","2","3","-1","-2","3","0","3","3","-1","1","3"],
  "ROUND3":["1","2","3","2","-2","2","2","3","6","1","1","3"],
  "ROUND4":["1","1","3","2","-2","1","5","2","9","0","4","6"],
  "ROUND5":["0","1","2","5","-2","1","5","2","8","3","7","6"],
  "ROUND6":["2","3","5","7","1","4","5","2","7","2","6","8"],
  "ROUND7":["2","3","5","6","1","3","8","2","9","5","8","8"],
  "ROUND8":["1","3","7","8","1","6","8","4","11","7","8","10"],
  "ROUND9":["3","3","10","10","1","5","8","4","10","7","8","13"],
  "ROUND10":["3","2","13","9","1","5","8","4","13","7","8","13"],
  "ROUND11":["2","2","16","9","4","5","7","7","12","10","7","13"],
  "ROUND12":["2","2","16","9","4","8","6","7","12","10","6","16"],
  "ROUND13":["2","1","15","8","7","8","5","10","15","10","6","19"],
  "ROUND14":["2","1","15","8","7","8","5","9","15","10","6","22"],
  "ROUND15":["1","0","18","11","7","7","8","9","17","10","6","24"],
  "ROUND16":["1","0","20","11","7","7","10","9","17","10","8","26"],
  "ROUND17":["0","0","19","10","10","7","13","12","16","12","11","28"],
  "ROUND18":["2","0","21","12","12","9","15","12","15","12","14","28"],
  "ROUND19":["2","0","23","11","11","11","18","14","18","12","14","30"],
  "ROUND20":["2","3","23","13","14","10","18","16","18","11","17","29"],
  "ROUND21":["1","3","25","13","17","13","21","15","20","10","17","29"],
  "ROUND22":["0","5","24","15","17","16","24","15","19","13","16","32"],
  "ROUND23":["0","4","24","14","17","19","24","15","22","13","18","34"],
  "ROUND24":["2","7","23","13","19","19","27","18","21","16","18","33"],
  "ROUND25":["4","7","22","13","19","19","30","18","23","18","20","33"],
  "ROUND26":["7","7","22","12","22","18","30","17","23","21","20","33"],
  "ROUND27":["7","6","22","11","22","20","32","17","26","24","23","32"],
  "ROUND28":["6","8","24","11","25","19","32","19","28","26","25","35"],
  "ROUND29":["6","10","24","11","25","19","32","19","31","25","27","35"],
  "ROUND30":["9","12","24","13","25","21","35","19","33","24","27","34"],
  "ROUND31":["9","12","23","13","24","20","38","18","36","27","27","37"],
  "ROUND32":["11","12","25","12","27","23","38","17","36","30","27","36"],
  "ROUND33":["11","14","24","12","27","26","41","16","39","29","29","36"],
  "ROUND34":["10","13","24","15","30","26","41","18","39","29","31","36"],
  "ROUND35":["10","13","23","17","33","29","40","21","39","31","31","35"],
  "ROUND36":["10","12","23","17","33","32","40","20","39","31","31","38"],
  "ROUND37":["13","11","22","17","35","35","43","19","42","31","33","37"],
  "ROUND38":["13","11","24","16","37","35","43","22","42","33","33","39"],
  "ROUND39":["12","11","24","16","40","38","42","21","42","33","33","42"],
  "ROUND40":["12","10","24","16","42","38","44","24","42","32","33","45"],
  "ROUND41":["11","9","27","19","44","41","43","27","41","32","35","45"],
  "ROUND42":["11","9","29","21","43","41","46","26","44","31","35","48"],
  "ROUND43":["11","9","31","20","43","43","49","26","47","31","34","48"],
  "ROUND44":["13","11","31","20","43","43","48","26","50","31","34","48"],
  "ROUND45":["12","11","34","20","45","45","48","29","49","31","34","48"],
  "ROUND46":["15","11","34","22","45","47","47","29","49","34","34","47"],
  "ROUND47":["15","11","37","21","45","50","47","28","49","34","33","50"],
  "ROUND48":["18","10","36","24","44","53","47","27","49","34","33","53"],
  "ROUND49":["18","10","38","24","46","53","47","30","49","33","33","53"],
  "ROUND50":["18","10","40","24","46","52","49","32","49","33","35","56"],
  "ROUND51":["20","12","39","24","48","55","48","32","49","35","38","56"],
  "ROUND52":["22","11","39","26","50","57","48","32","52","38","38","55"],
  "ROUND53":["21","14","39","29","53","56","47","32","52","38","38","55"],
  "ROUND54":["21","14","42","29","52","56","47","32","51","38","38","58"],
  "ROUND55":["21","16","44","28","52","56","46","35","51","38","41","58"],
  "ROUND56":["24","15","47","27","52","56","49","34","54","38","40","58"],
  "ROUND57":["27","18","50","27","51","55","49","34","53","41","40","57"],
  "ROUND58":["27","20","52","29","50","55","49","37","55","44","39","57"],
  "ROUND59":["27","22","52","29","53","55","49","37","55","46","39","56"],
  "ROUND60":["29","22","51","32","52","58","49","39","54","49","41","58"],
  "ROUND61":["28","22","51","32","55","58","49","42","54","48","41","58"],
  "ROUND62":["30","22","50","32","55","60","51","42","57","50","41","58"],
  "ROUND63":["30","25","49","31","57","63","51","42","57","50","43","58"],
  "ROUND64":["30","24","49","31","60","63","53","42","60","49","45","58"],
  "ROUND65":["30","27","48","33","59","63","56","45","62","51","47","57"],
  "ROUND66":["29","30","51","36","58","62","56","44","65","54","47","56"],
  "ROUND67":["28","33","54","39","61","62","56","43","64","54","47","55"],
  "ROUND68":["30","36","54","39","61","65","56","42","63","57","46","57"],
  "ROUND69":["33","36","56","42","60","67","58","45","65","56","46","56"],
  "ROUND70":["36","36","55","41","60","66","57","48","68","56","46","59"],
  "ROUND71":["38","39","57","41","60","65","57","48","70","58","45","62"],
  "ROUND72":["37","39","59","40","63","65","57","48","73","58","47","62"],
  "ROUND73":["39","41","61","42","63","67","59","48","75","60","49","64"],
  "ROUND74":["41","41","60","44","66","70","59","48","75","60","48","64"],
  "ROUND75":["41","40","63","47","66","69","59","51","75","63","47","63"],
  "ROUND76":["40","39","66","46","69","69","58","51","78","66","47","63"],
  "ROUND77":["39","39","69","46","68","69","58","54","77","69","50","62"],
  "ROUND78":["39","39","69","49","71","69","57","54","77","69","50","61"],
  "ROUND79":["39","38","72","51","74","69","59","57","80","68","49","60"],
  "ROUND80":["39","38","71","51","73","69","61","60","83","68","51","60"]
}
