{
  "ID":["0","1","2","3","4","5","6","7","8","9","10","11"],
  "ROUND1":["0","0","3","-1","-1","3","3","3","0","0","-1","-1"],
  "ROUND2":["0","0","3","-2","-1","6","6","5","0","0","1","-2"],
  "ROUND3":["0","0","3","0","1","6","8","8","2","-1","1","-2"],
  "ROUND4":["2","2","5","0","4","6","7","8","5","1","0","-2"],
  "ROUND5":["1","5","5","0","6","6","7","10","7","1","2","-2"],
  "ROUND6":["3","5","4","-1","6","6","10","13","7","1","4","-2"],
  "ROUND7":["2","7","7","-1","9","6","9","15","9","3","7","-3"],
  "ROUND8":["1","9","7","1","9","9","9","15","9","2","7","0"],
  "ROUND9":["1","9","6","4","8","11","9","18","9","2","9","0"],
  "ROUND10":["3","9","6","6","8","14","8","21","12","1","9","-1"],
  "ROUND11":["6","11","8","8","10","17","8","20","12","1","9","-2"],
  "ROUND12":["6","13","11","11","9","16","7","23","11","4","11","-2"],
  "ROUND13":["6","15","11","11","9","16","6","23","14","6","11","-2"],
  "ROUND14":["6","18","10","14","8","16","6","22","14","6","14","-2"],
  "ROUND15":["5","18","10","13","11","18","9","21","17","8","14","-2"],
  "ROUND16":["4","21","10","13","14","20","12","20","19","7","13","1"],
  "ROUND17":["6","24","12","12","17","20","12","19","18","10","12","4"],
  "ROUND18":["9","26","15","12","19","19","15","18","18","13","11","3"],
  "ROUND19":["12","26","15","11","18","21","18","20","20","15","10","6"],
  "ROUND20":["12","26","14","10","18","21","18","19","23","18","13","6"],
  "ROUND21":["12","26","14","9","18","21","17","22","26","21","12","6"],
  "ROUND22":["12","25","14","12","18","21","19","24","25","21","15","6"],
  "ROUND23":["11","25","17","12","21","21","22","23","28","21","14","5"],
  "ROUND24":["10","25","16","12","24","20","22","23","31","24","13","8"],
  "ROUND25":["10","28","19","15","23","20","22","23","31","24","12","7"],
  "ROUND26":["13","30","18","14","25","23","25","22","34","24","11","7"],
  "ROUND27":["13","30","18","14","27","23","25","22","34","26","11","7"],
  "ROUND28":["16","32","18","13","27","23","25","24","34","26","11","7"],
  "ROUND29":["15","35","18","13","27","22","25","27","34","26","11","7"],
  "ROUND30":["14","37","18","16","30","21","27","27","37","26","10","7"],
  "ROUND31":["14","37","18","15","32","23","26","26","40","29","10","10"],
  "ROUND32":["17","36","20","15","32","22","26","29","42","31","12","10"],
  "ROUND33":["19","38","20","15","32","22","28","31","42","33","12","12"],
  "ROUND34":["18","38","22","17","35","22","31","30","44","36","14","11"],
  "ROUND35":["21","38","22","16","38","22","31","30","44","39","13","10"],
  "ROUND36":["24","37","22","16","37","22","34","30","44","42","13","9"],
  "ROUND37":["27","36","22","15","37","21","37","32","47","41","16","11"],
  "ROUND38":["27","38","22","15","39","23","37","34","47","43","18","11"],
  "ROUND39":["29","38","24","14","41","25","39","34","49","43","18","14"],
  "ROUND40":["29","41","24","16","40","24","41","36","51","46","18","14"],
  "ROUND41":["28","41","27","15","40","23","41","39","54","45","18","17"],
  "ROUND42":["28","43","26","15","40","26","43","41","56","45","17","20"],
  "ROUND43":["27","45","25","15","42","29","43","43","58","47","20","22"],
  "ROUND44":["26","48","25","14","44","32","42","42","61","47","23","24"],
  "ROUND45":["29","50","28","14","44","34","41","42","60","47","23","24"],
  "ROUND46":["29","50","31","17","47","34","40","42","59","47","23","23"],
  "ROUND47":["29","52","31","17","47","34","40","42","59","47","23","25"],
  "ROUND48":["32","54","31","17","47","37","42","41","59","47","22","25"],
  "ROUND49":["34","57","33","20","46","37","44","41","58","46","25","27"],
  "ROUND50":["33","56","33","23","45","37","47","44","57","49","28","26"],
  "ROUND51":["36","56","33","23","44","37","49","44","57","51","27","29"],
  "ROUND52":["35","58","33","25","46","40","49","46","57","53","27","31"],
  "ROUND53":["34","58","35","25","46","40","52","46","57","52","30","33"],
  "ROUND54":["37","57","38","28","45","42","54","45","59","54","30","33"],
  "ROUND55":["39","60","40","30","45","42","54","47","61","56","29","33"],
  "ROUND56":["39","60","42","32","45","42","53","47","63","56","31","36"],
  "ROUND57":["39","59","42","34","47","42","55","50","63","58","33","38"],
  "ROUND58":["42","59","42","33","47","42","55","50","63","57","36","38"],
  "ROUND59":["45","62","41","32","47","42","55","53","63","57","35","38"],
  "ROUND60":["44","62","40","32","47","41","58","56","63","57","38","38"],
  "ROUND61":["46","64","40","32","50","44","60","58","65","56","40","37"],
  "ROUND62":["45","63","40","31","53","47","63","58","65","56","42","39"],
  "ROUND63":["45","63","40","31","55","46","66","60","67","55","44","42"],
  "ROUND64":["45","65","42","34","54","46","66","60","69","54","47","44"],
  "ROUND65":["47","68","45","33","54","46","68","62","68","53","50","46"],
  "ROUND66":["47","67","44","33","57","45","68","62","71","56","49","49"],
  "ROUND67":["47","69","43","36","60","47","71","62","71","55","49","48"],
  "ROUND68":["49","72","45","36","60","47","73","64","70","57","49","50"],
  "ROUND69":["49","75","44","35","63","50","72","67","69","59","49","52"],
  "ROUND70":["51","77","44","35","65","52","72","67","71","61","49","52"],
  "ROUND71":["54","80","44","34","65","51","72","70","71","61","48","52"],
  "ROUND72":["57","80","47","33","67","50","74","69","74","63","50","52"],
  "ROUND73":["60","82","50","32","67","50","76","69","73","63","53","51"],
  "ROUND74":["60","82","50","34","69","49","75","68","76","63","56","54"],
  "ROUND75":["63","85","49","36","71","52","78","68","75","62","55","54"],
  "ROUND76":["62","84","49","36","73","55","78","67","78","62","58","56"],
  "ROUND77":["65","84","48","39","73","58","77","66","78","62","57","59"],
  "ROUND78":["65","86","47","42","73","61","79","66","78","61","56","62"],
  "ROUND79":["65","89","49","45","72","61","81","65","80","60","59","64"],
  "ROUND80":["67","89","51","44","72","63","81","67","83","60","59","64"]
}
